examples/__init__.py
examples/ode/__init__.py
examples/ode/case_1.py
examples/ode/case_1_model.py
examples/ode/case_2.py
examples/ode/case_2_load.py
examples/ode/case_2_model.py
examples/ode/case_3.py
examples/ode/case_3_model.py
examples/ode/case_4.py
examples/ode/case_4_model.py
examples/ode/case_5.py
examples/ode/case_5_model.py
examples/ode/dow_chemical.py
examples/ode/dow_chemical_oed.py
examples/ode/monod_kinetics.py
examples/ode/test_ode.py
pydex/__init__.py
pydex/core/__init__.py
pydex/core/designer.py
pydex/core/logger.py
pydex/core/bnb/__init__.py
pydex/core/bnb/node.py
pydex/core/bnb/tree.py
pydex/utils/__init__.py
pydex/utils/dynamic_experiment_plotter.py
pydex/utils/trellis_plotter.py
pydex-0.0.9.dist-info/LICENSE
pydex-0.0.9.dist-info/METADATA
pydex-0.0.9.dist-info/WHEEL
pydex-0.0.9.dist-info/top_level.txt
pydex-0.0.9.dist-info/RECORD
