Metadata-Version: 2.1
Name: pydex
Version: 0.0.9
Summary: A Python package for optimal experiment design.
Home-page: https://github.com/KennedyPutraKusumo/pydex
Author: Kennedy Putra Kusumo
Author-email: kennedy.putra.kusumo@gmail.com
Classifier: Programming Language :: Python :: 3
Classifier: License :: OSI Approved :: MIT License
Classifier: Operating System :: OS Independent
Requires-Python: >=3.6
License-File: LICENSE
Requires-Dist: matplotlib
Requires-Dist: numdifftools
Requires-Dist: scipy
Requires-Dist: cvxpy
Requires-Dist: dill
Requires-Dist: numpy
Requires-Dist: corner
